pycombo/__init__.py
pycombo/_combo.cpython-311-darwin.so
pycombo/misc.py
pycombo/pyCombo.py
pycombo-0.1.8.dist-info/AUTHORS.rst
pycombo-0.1.8.dist-info/LICENSE
pycombo-0.1.8.dist-info/LICENSE.txt
pycombo-0.1.8.dist-info/METADATA
pycombo-0.1.8.dist-info/WHEEL
pycombo-0.1.8.dist-info/RECORD
