Metadata-Version: 2.1
Name: pycombo
Version: 0.1.8
Summary: Python wrapper around Combo network partitioning algorithm (C++)
Home-page: https://github.com/Casyfill/pyCombo
License: MIT
Keywords: Networks,Graph Theory,Mathematics,network,graph,discrete mathematics,math
Author: Philipp
Author-email: casyfill@gmail.com
Requires-Python: >=3.8,<4.0
Classifier: Development Status :: 4 - Beta
Classifier: Intended Audience :: Developers
Classifier: Intended Audience :: Science/Research
Classifier: License :: OSI Approved :: MIT License
Classifier: Operating System :: OS Independent
Classifier: Programming Language :: Python :: 3
Classifier: Programming Language :: Python :: 3.8
Classifier: Programming Language :: Python :: 3.9
Classifier: Programming Language :: Python :: 3.10
Classifier: Programming Language :: Python :: 3.11
Classifier: Programming Language :: Python :: 3.12
Classifier: Programming Language :: Python :: 3 :: Only
Classifier: Topic :: Scientific/Engineering :: Bio-Informatics
Classifier: Topic :: Scientific/Engineering :: Information Analysis
Classifier: Topic :: Scientific/Engineering :: Mathematics
Classifier: Topic :: Scientific/Engineering :: Physics
Classifier: Topic :: Software Development :: Libraries :: Python Modules
Project-URL: Bug Tracker, https://github.com/Casyfill/pyCombo/issues
Project-URL: Source Code, https://github.com/Casyfill/pyCombo
